{
  "main": {
    "id": "7b604722573c972e",
    "type": "split",
    "children": [
      {
        "id": "f2b2b79364139584",
        "type": "tabs",
        "children": [
          {
            "id": "5455bfad12b0e1f5",
            "type": "leaf",
            "state": {
              "type": "graph",
              "state": {},
              "icon": "lucide-git-fork",
              "title": "Vista gráfica"
            }
          }
        ]
      }
    ],
    "direction": "vertical"
  },
  "left": {
    "id": "8fb20c31277604e3",
    "type": "split",
    "children": [
      {
        "id": "ed54d38e80913763",
        "type": "tabs",
        "children": [
          {
            "id": "ae9f60691de7500f",
            "type": "leaf",
            "state": {
              "type": "file-explorer",
              "state": {
                "sortOrder": "alphabetical",
                "autoReveal": false
              },
              "icon": "lucide-folder-closed",
              "title": "Explorador de archivos"
            }
          },
          {
            "id": "76cfaf615b6dff22",
            "type": "leaf",
            "state": {
              "type": "search",
              "state": {
                "query": "",
                "matchingCase": false,
                "explainSearch": false,
                "collapseAll": false,
                "extraContext": false,
                "sortOrder": "alphabetical"
              },
              "icon": "lucide-search",
              "title": "Buscar"
            }
          },
          {
            "id": "47a1a1c3bd57603e",
            "type": "leaf",
            "state": {
              "type": "bookmarks",
              "state": {},
              "icon": "lucide-bookmark",
              "title": "Marcadores"
            }
          }
        ]
      }
    ],
    "direction": "horizontal",
    "width": 300,
    "collapsed": true
  },
  "right": {
    "id": "003c1de5181e70e8",
    "type": "split",
    "children": [
      {
        "id": "b56dead33a1b75ff",
        "type": "tabs",
        "children": [
          {
            "id": "ff212ab110c51cdc",
            "type": "leaf",
            "state": {
              "type": "backlink",
              "state": {
                "collapseAll": false,
                "extraContext": false,
                "sortOrder": "alphabetical",
                "showSearch": false,
                "searchQuery": "",
                "backlinkCollapsed": false,
                "unlinkedCollapsed": true
              },
              "icon": "links-coming-in",
              "title": "Enlaces entrantes"
            }
          },
          {
            "id": "be026f2b2e47a780",
            "type": "leaf",
            "state": {
              "type": "outgoing-link",
              "state": {
                "linksCollapsed": false,
                "unlinkedCollapsed": true
              },
              "icon": "links-going-out",
              "title": "Enlaces salientes"
            }
          },
          {
            "id": "7a0abc3763671c7a",
            "type": "leaf",
            "state": {
              "type": "tag",
              "state": {
                "sortOrder": "frequency",
                "useHierarchy": true,
                "showSearch": false,
                "searchQuery": ""
              },
              "icon": "lucide-tags",
              "title": "Etiquetas"
            }
          },
          {
            "id": "3c72bb4e1a6ad6f0",
            "type": "leaf",
            "state": {
              "type": "all-properties",
              "state": {
                "sortOrder": "frequency",
                "showSearch": false,
                "searchQuery": ""
              },
              "icon": "lucide-archive",
              "title": "Todas las propiedades"
            }
          },
          {
            "id": "7e0e2f6e5a0e68ce",
            "type": "leaf",
            "state": {
              "type": "outline",
              "state": {
                "followCursor": false,
                "showSearch": false,
                "searchQuery": ""
              },
              "icon": "lucide-list",
              "title": "Esquema"
            }
          }
        ]
      }
    ],
    "direction": "horizontal",
    "width": 300,
    "collapsed": true
  },
  "left-ribbon": {
    "hiddenItems": {
      "switcher:Abrir selector rápido": false,
      "graph:Abrir vista gráfica": false,
      "canvas:Crear nuevo lienzo": false,
      "daily-notes:Abrir la nota de hoy": false,
      "templates:Insertar plantilla": false,
      "command-palette:Abrir paleta de comandos": false,
      "bases:Crear nueva base": false
    }
  },
  "active": "5455bfad12b0e1f5",
  "lastOpenFiles": [
    "Sin título 1.base",
    "Sin título.base",
    "arquitectura.md",
    "Sin título.canvas",
    "flujos.md",
    "esquema-db.md"
  ]
}